odoo10_addon_l10n_fr_account_invoice_import_factur_x-10.0.1.0.0.99.dev3-py2.7-nspkg.pth
odoo/addons/l10n_fr_account_invoice_import_factur-x/README.rst
odoo/addons/l10n_fr_account_invoice_import_factur-x/__init__.py
odoo/addons/l10n_fr_account_invoice_import_factur-x/__manifest__.py
odoo/addons/l10n_fr_account_invoice_import_factur-x/i18n/l10n_fr_account_invoice_import_factur-x.pot
odoo/addons/l10n_fr_account_invoice_import_factur-x/static/description/icon.png
odoo/addons/l10n_fr_account_invoice_import_factur-x/wizard/__init__.py
odoo/addons/l10n_fr_account_invoice_import_factur-x/wizard/account_invoice_import.py
odoo10_addon_l10n_fr_account_invoice_import_factur_x-10.0.1.0.0.99.dev3.dist-info/METADATA
odoo10_addon_l10n_fr_account_invoice_import_factur_x-10.0.1.0.0.99.dev3.dist-info/RECORD
odoo10_addon_l10n_fr_account_invoice_import_factur_x-10.0.1.0.0.99.dev3.dist-info/WHEEL
odoo10_addon_l10n_fr_account_invoice_import_factur_x-10.0.1.0.0.99.dev3.dist-info/namespace_packages.txt
odoo10_addon_l10n_fr_account_invoice_import_factur_x-10.0.1.0.0.99.dev3.dist-info/top_level.txt
